ansi_capture/__init__.py
ansi_capture-0.0.0.2.dist-info/METADATA
ansi_capture-0.0.0.2.dist-info/WHEEL
ansi_capture-0.0.0.2.dist-info/entry_points.txt
ansi_capture-0.0.0.2.dist-info/top_level.txt
ansi_capture-0.0.0.2.dist-info/RECORD
