Metadata-Version: 2.1
Name: ansi-capture
Version: 0.0.0.2
Summary: Virtual ANSI terminal capture (for escape sequences). Handles most Linux and xterm sequences.
Home-page: https://github.com/cacticouncil/ansi_capture
Author: Jeremiah Blanchard
Author-email: jjb@eng.ufl.edu
License: GPL 3
Platform: UNKNOWN
